{
	"leftPins":{
		"column_widths": [50, 30, 30, 30, 30],
		"subpins_colors": ["#ff66cc", "#ff66cc", "#ff66cc", "#ff66cc", "#ff66cc"],
		"list": [
			{
				"label": "PC1",
				"color": "#0099ff",
				"subPins": ["RX", "NSS", "BKIN", "SDA"]
			},
			{
				"label": "PC2", 
				"color": "#0099ff",
				"subPins": ["RTS", "AETR", "BKIN", "", "SCL"]
			},
			{
				"label": "PC3",
				"color": "#0099ff", 
				"subPins": ["CH1N", "", "CH3", ""]
			},
			{
				"label": "PC4",
				"color": "#ffb300",
				"subPins": ["CH1CH2N", "MCO", "CH4", "A2"]
			},
			{
				"label": "PC6",
				"color": "#0099ff",
				"subPins": ["SDA", "", "C1C3N", "MOSI"]
			},
			{
				"label": "PC7",
				"color": "#0099ff",
				"subPins": ["SCL", "SWIO", "CH3N", "AETR2"]
			}
		]
	},
	"rightPins": {
		"column_widths": [30, 30, 30, 30, 30],
		"subpins_colors": ["#ff66cc", "#ff66cc", "#ff66cc", "#ff66cc", "#ff66cc"],
		"list": [
			{
				"label": "PC0",
				"color": "#0099ff",
				"subPins": ["CH3", "CH3", "NSS", "TX"]
			},
			{
				"label": "VDD",
				"color": "#0099ff",
				"subPins": []
			},
			{
				"label": "VSS",
				"color": "#ff66cc",
				"subPins": []
			},
			{
				"label": "PA2",
				"color": "#9933ff",
				"subPins": ["A0", "OSCO", "CH2N", "", "OPP0"]
			},
			{
				"label": "PA1",
				"color": "#9933ff",
				"subPins": ["A1", "OSCI", "CH2", "", "OPN0"]
			},
			{
				"label": "PD7",
				"color": "#9933ff", 
				"subPins": ["", "NRST", "CH4", "CK"]
			}
		]
	}
}